gtFrame/__init__.py
gtFrame/basic.py
gtFrame/direction.py
gtFrame/position.py
gtFrame/rotation.py
gtFrame-1.2.3.dist-info/LICENSE
gtFrame-1.2.3.dist-info/METADATA
gtFrame-1.2.3.dist-info/WHEEL
gtFrame-1.2.3.dist-info/top_level.txt
gtFrame-1.2.3.dist-info/RECORD
