Metadata-Version: 2.1
Name: gtFrame
Version: 1.2.3
Summary: A simple library for working with frames of reference
Author-email: "Roko Jukic (bluePlatinum)" <jukic.rok@gmail.com>
License: MIT License
Project-URL: Homepage, https://github.com/bluePlatinum/gtFrame
Classifier: Programming Language :: Python :: 3
Classifier: License :: OSI Approved :: MIT License
Classifier: Operating System :: OS Independent
Requires-Python: >=3.7
License-File: LICENSE
Requires-Dist: numpy
Requires-Dist: scipy
